{
  "version": "0.2",
  "language": "en",
  "dictionaries": [
    "en_US",
    "softwareTerms",
    "html",
    "css",
    "cpp",
    "bash",
    "php"
  ],
  "ignorePaths": [
    "**/.git/**",
    "**/node_modules/**",
    "**/vscode-extension/**",
    ".vscode",
    "package-lock.json",
    "report"
  ],
  "words": [
    "AGPL",
    "ATSYNC",
    "Affero",
    "Algis",
    "Aquilina",
    "AsciiDoc",
    "AsciiDoctor",
    "Ater",
    "Biffle",
    "CFLAGS",
    "COPYPASTE",
    "CSS",
    "Clang",
    "Crashlytics",
    "DeepSource",
    "DeepSourceLabs",
    "ETeuvxo",
    "ETeuxo",
    "ETuvxo",
    "ETuxo",
    "Eeuvxo",
    "Eeuxo",
    "Euvxo",
    "Euxo",
    "FLOATLOOPCOUNTER",
    "GETPW",
    "GPLP",
    "Git",
    "GitHub",
    "Gitpod",
    "Google",
    "Guillaume",
    "INCOMP",
    "INSECUREAPI",
    "Imgbot",
    "JetBrains",
    "LIBKERN",
    "Linux",
    "MKSTEMP",
    "MSGSEND",
    "Mackup",
    "NOESCAPE",
    "NONARC",
    "NSCFERROR",
    "OFFSETOF",
    "STRCPY",
    "TextMate",
    "UNCHECKEDRETURN",
    "Visual Studio",
    "Vitor",
    "Vivek",
    "VivekGite",
    "WIPO",
    "Wcall",
    "Wdefaulted",
    "Weffc",
    "Wextra",
    "Windows",
    "Wmemset",
    "Wno",
    "Woverriding",
    "Wreturn",
    "Wsizeof",
    "Xcode",
    "Zsh",
    "Zunit",
    "adoc",
    "agplp",
    "anyobject",
    "aps",
    "argc",
    "argv",
    "autobuild",
    "autocrlf",
    "autofix",
    "autopep",
    "autorelease",
    "autoreleasing",
    "bastet",
    "bcmp",
    "bcopy",
    "bzero",
    "calibreapp",
    "cbp",
    "cggeometry",
    "changelog’s",
    "climits",
    "codeql",
    "cplusplus",
    "csharp",
    "cspell",
    "cstring",
    "ctor",
    "cyberciti",
    "cyclomatic",
    "cætéra",
    "dabutvin",
    "deadcode",
    "deadstores",
    "dealloc",
    "deallocator",
    "deinit",
    "dependabot",
    "discardable",
    "donotpresent",
    "dotfiles",
    "dtor",
    "dylib",
    "editorconfig",
    "elif",
    "envc",
    "envp",
    "esktop",
    "esolang",
    "euo",
    "eval",
    "excludesfile",
    "fcaret",
    "fdiagnostics",
    "fdiagnostics-fixit-info",
    "fdiagnostics-parseable-fixits",
    "ffs",
    "fgnat",
    "fgnu",
    "fident",
    "fileprivate",
    "fixit",
    "fixits",
    "fkirc",
    "flatmap",
    "fno",
    "freebsd",
    "fshow",
    "fstandalone",
    "ftime",
    "ftrapv",
    "gaurav",
    "gcc",
    "gch",
    "gcic",
    "gcno",
    "gitconfig",
    "githubusercontent",
    "gitlab",
    "gitpod",
    "gitsubmodule",
    "gkd",
    "gmv",
    "gofmt",
    "gomod",
    "gpgsign",
    "gtag",
    "guillaumealgis",
    "gunstage",
    "howto",
    "ibinspectable",
    "ibiqlik",
    "iboutlet",
    "icns",
    "ifndef",
    "imgbotconfig",
    "iml",
    "ipch",
    "ipr",
    "isequal",
    "isort",
    "issuehunt",
    "ivars",
    "iws",
    "jonreid",
    "jsonlint",
    "keychain",
    "konqueror",
    "ksh",
    "lai",
    "latomic",
    "lfs",
    "liberapay",
    "llu",
    "lnk",
    "localizability",
    "loweralpha",
    "lsi",
    "lstdc",
    "lucaslarson",
    "macOS",
    "malloc",
    "markdownlint",
    "mergetool",
    "minuti",
    "minutiæ",
    "mkdir",
    "mkdirp",
    "mpeltonen",
    "mpi",
    "msix",
    "msm",
    "msp",
    "multiline",
    "ncb",
    "nfs",
    "nixCraft",
    "nodoc",
    "noninfringement",
    "nonlocalized",
    "nonnull",
    "nsgeometry",
    "nslocalizedstring",
    "nsobject",
    "nuget",
    "nvim",
    "nvuillam",
    "objc",
    "ogs",
    "ohmyzsh",
    "omz",
    "opensdf",
    "optin",
    "ossar",
    "osxkeychain",
    "otechie",
    "parseable",
    "patreon",
    "pbxproj",
    "pbxuser",
    "pch",
    "peter-evans",
    "plutil",
    "precompose",
    "printf",
    "pthread",
    "pyenv",
    "pyproject",
    "rbenv",
    "replstate",
    "rerere",
    "robbyrussell",
    "runtimes",
    "rustup",
    "sarif",
    "sbt-idea",
    "scc",
    "sdf",
    "shell",
    "shfmt",
    "signedness",
    "simctl",
    "slo",
    "smod",
    "sobolevn",
    "standardjs",
    "standardrb",
    "stefanzweifel",
    "streetsidesoftware",
    "strnlen",
    "sublicensing",
    "submodule",
    "svclog",
    "swiftlint",
    "symvers",
    "tetris",
    "textconv",
    "tidelift",
    "timey",
    "tli",
    "toclevels",
    "toplevel",
    "tsmerge",
    "typecheck",
    "typoci",
    "unbuildable",
    "uncommenting",
    "unsequenced",
    "unstage",
    "unstagers",
    "unstaging",
    "valist",
    "venv",
    "vfork",
    "visualstudio",
    "vsmarketplacebadge",
    "webfont",
    "webp",
    "webtv",
    "wontfix",
    "xab",
    "xargs",
    "xccheckout",
    "xcconfig",
    "xclang",
    "xcrun",
    "xcscmblueprint",
    "xcsettings",
    "xcshareddata",
    "xctest",
    "xctfail",
    "xcuserdata",
    "xcworkspacedata",
    "yamllint",
    "zcalc",
    "zcompdump",
    "zdharma",
    "zlogin",
    "zlogout",
    "zprofile",
    "zrecompile",
    "zsdoc",
    "zsh",
    "zshelldoc",
    "zshenv",
    "zshrc",
    "zwc"
  ],
  "flagWords": [
    "hte",
    "Lucaslarson",
    "lucasLarson"
  ]
}
